pyunify/__init__.py
pyunify/obj.py
pyunify-0.0.1.dist-info/METADATA
pyunify-0.0.1.dist-info/WHEEL
pyunify-0.0.1.dist-info/licenses/LICENSE
pyunify-0.0.1.dist-info/RECORD
