Metadata-Version: 2.1
Name: pyunify
Version: 0.0.1
Summary: Python implementation using the JSON-Unify specifcation
Project-URL: Homepage, https://github.com/JSON-UNIFY
Project-URL: Bug Tracker, https://github.com/JSON-UNIFY
Author-email: Ron Itelman & Cameron Prybol <ron@itelman.ai>
License-File: LICENSE
Classifier: License :: OSI Approved :: MIT License
Classifier: Operating System :: OS Independent
Classifier: Programming Language :: Python :: 3
Requires-Python: >=3.7
